README.rst
setup.cfg
setup.py
conf4ini/__init__.py
conf4ini/config.py
conf4ini.egg-info/PKG-INFO
conf4ini.egg-info/SOURCES.txt
conf4ini.egg-info/dependency_links.txt
conf4ini.egg-info/requires.txt
conf4ini.egg-info/top_level.txt
conf4ini/test/__init__.py