Metadata-Version: 2.1
Name: conf4ini
Version: 1.0.0
Summary: a simple config reader for *.ini files
Home-page: https://github.com/tony-is-coding/conf4ini
Author: tony-is-coding
Author-email: newbiwtan@163.com
Maintainer: tony-is-coding
License: UNKNOWN
Platform: UNKNOWN
Classifier: Programming Language :: Python :: 3
Classifier: License :: OSI Approved :: MIT License
Classifier: Operating System :: OS Independent
Provides-Extra: docs
